{
  "products": [
    {
      "id": 1,
      "name": "눈 덮힌 아사쿠사",
      "provider": "피에르 장",
      "price": 58000,
      "image": "/images/image001.png"
    },
    {
      "id": 2,
      "name": "설산 아래 궁",
      "provider": "피에르 장",
      "price": 3230000,
      "image": "/images/image002.png"
    },
    {
      "id": 3,
      "name": "얼어붙은 호수",
      "provider": "피에르 장",
      "price": 700000,
      "image": "/images/image003.png"
    },
    {
      "id": 4,
      "name": "낭만 가득한 뉴욕",
      "provider": "피에르 장",
      "price": 1900000,
      "image": "/images/image004.png"
    },
    {
      "id": 5,
      "name": "얼어붙은 자유",
      "provider": "피에르 장",
      "price": 99000,
      "image": "/images/image005.png"
    },
    {
      "id": 6,
      "name": "1월의 에펠탑",
      "provider": "피에르 장",
      "price": 104000,
      "image": "/images/image006.png"
    }
  ]
}
